easy_start_images/__init__.py
easy_start_images/imgkit.py
easy_start_images/pillow.py
easy_start_images-0.1.6.dist-info/licenses/LICENSE
easy_start_images-0.1.6.dist-info/METADATA
easy_start_images-0.1.6.dist-info/WHEEL
easy_start_images-0.1.6.dist-info/top_level.txt
easy_start_images-0.1.6.dist-info/RECORD
