Metadata-Version: 2.4
Name: easy-start-images
Version: 0.1.6
Summary: 一个简单易用的图像处理Python库，提供了在图片上绘制文本和将HTML转换为图像的功能。
Home-page: https://gitee.com/guolei19850528/easy_start_images
Author: guolei
Author-email: 174000902@qq.com
Classifier: Programming Language :: Python :: 3
Classifier: License :: OSI Approved :: MIT License
Classifier: Operating System :: OS Independent
Requires-Python: >=3.6
License-File: LICENSE
Requires-Dist: imgkit
Requires-Dist: Pillow
Dynamic: author
Dynamic: author-email
Dynamic: classifier
Dynamic: description
Dynamic: description-content-type
Dynamic: home-page
Dynamic: license-file
Dynamic: requires-dist
Dynamic: requires-python
Dynamic: summary
